{"ad_search_list":null,"banner_dark":{"uri":"33a57000197f34889bc27","url_list":["https://p3-sign.douyinpic.com/obj/33a57000197f34889bc27?x-expires=1722340800\u0026x-signature=cGBsHdM1Z8dt18R47YbS%2Fi5pZ1M%3D\u0026from=568394430","https://p26-sign.douyinpic.com/obj/33a57000197f34889bc27?x-expires=1722340800\u0026x-signature=cz2nwhTDUyjwfFxL1aUFN112yzs%3D\u0026from=568394430","https://p9-sign.douyinpic.com/obj/33a57000197f34889bc27?x-expires=1722340800\u0026x-signature=a%2FAJ%2BCbUwc8NhIP4Xw8RATr64M4%3D\u0026from=568394430"]},"banner_light":{"uri":"33a580000cefdf44e9f76","url_list":["https://p3-sign.douyinpic.com/obj/33a580000cefdf44e9f76?x-expires=1722340800\u0026x-signature=HtZkPKEb3iXicxp0mbLhjAmpXQ0%3D\u0026from=568394430","https://p26-sign.douyinpic.com/obj/33a580000cefdf44e9f76?x-expires=1722340800\u0026x-signature=8430tB9Hpk0VlO1zBlfnVo7jbhc%3D\u0026from=568394430","https://p9-sign.douyinpic.com/obj/33a580000cefdf44e9f76?x-expires=1722340800\u0026x-signature=UL1%2BSnUVSrfeefmF0xg7TQhAkuA%3D\u0026from=568394430"]},"board_tabs":[],"data":{"active_time":"2024-07-30 14:12:50","recommend_list":null,"share_info":{"share_link_desc":"我在看抖音热榜，发现最火的内容，赶快来看！戳这里\u003e\u003e","share_title":"我在看抖音热榜，发现最火的内容，赶快来看！","share_url":"https://www.iesdouyin.com/share/billboard/?id=0"},"trending_list":[],"word_list":[{"aweme_infos":null,"can_extend_detail":false,"challenge_id":"","discuss_video_count":0,"display_style":0,"drift_info":null,"event_time":1722304681,"group_id":"7395422945608701184","hot_value":9190908,"hotlist_param":"{\"version\":1}","label":0,"position":1,"related_words":null,"sentence_id":"1780590","video_count":1,"view_count":594240,"word":"英国“破产”后果有多严重","word_cover":{"uri":"tos-cn-p-0015/oEfen0XAABBED1gmsEDhCmIapEcFBY9m2F7Ayz","url_list":["https://p9-sign.douyinpic.com/tos-cn-p-0015/oEfen0XAABBED1gmsEDhCmIapEcFBY9m2F7Ayz~noop.jpeg?lk3s=bfd515bb\u0026x-expires=1722340800\u0026x-signature=lEayn79LgN%2FxpLmV3W3asNPpweo%3D\u0026from=3218412987","https://p3-sign.douyinpic.com/tos-cn-p-0015/oEfen0XAABBED1gmsEDhCmIapEcFBY9m2F7Ayz~noop.jpeg?lk3s=bfd515bb\u0026x-expires=1722340800\u0026x-signature=Kt31ymY6s2DJHME6qdT9fbBBZx4%3D\u0026from=3218412987","https://p26-sign.douyinpic.com/tos-cn-p-0015/oEfen0XAABBED1gmsEDhCmIapEcFBY9m2F7Ayz~noop.jpeg?lk3s=bfd515bb\u0026x-expires=1722340800\u0026x-signature=OyVhM7%2FH5BC9gD4XYFSIOvg9iqY%3D\u0026from=3218412987"]},"word_sub_board":null,"word_type":1},{"aweme_infos":null,"can_extend_detail":false,"challenge_id":"","discuss_video_count":0,"display_style":0,"drift_info":null,"event_time":1722237199,"group_id":"7395892965682959642","hot_value":8910397,"hotlist_param":"{\"version\":1}","label":3,"position":2,"related_words":null,"sentence_id":"1779921","video_count":2,"view_count":4290959,"word":"况盛发律师声明","word_cover":{"uri":"tos-cn-i-0813/ocHmsfD0AAAoA9ojgIFKpgCDVfyOVa0EAACFOQ","url_list":["https://p26-sign.douyinpic.com/tos-cn-i-0813/ocHmsfD0AAAoA9ojgIFKpgCDVfyOVa0EAACFOQ~noop.jpeg?lk3s=bfd515bb\u0026x-expires=1722340800\u0026x-signature=6B07i4XmoqGIxTL3HnIZohxg%2BOg%3D\u0026from=3218412987","https://p3-sign.douyinpic.com/tos-cn-i-0813/ocHmsfD0AAAoA9ojgIFKpgCDVfyOVa0EAACFOQ~noop.jpeg?lk3s=bfd515bb\u0026x-expires=1722340800\u0026x-signature=e5lq7PzCI74wHe7HdtsH%2B1%2FQ1Io%3D\u0026from=3218412987","https://p11-sign.douyinpic.com/tos-cn-i-0813/ocHmsfD0AAAoA9ojgIFKpgCDVfyOVa0EAACFOQ~noop.jpeg?lk3s=bfd515bb\u0026x-expires=1722340800\u0026x-signature=7TzU1UMdiS7jRhCEtSaCIapdr1U%3D\u0026from=3218412987"]},"word_sub_board":null,"word_type":1},{"aweme_infos":null,"can_extend_detail":false,"challenge_id":"","discuss_video_count":0,"display_style":0,"drift_info":null,"event_time":1722303929,"group_id":"7387338803071440164","hot_value":7799666,"hotlist_param":"{\"version\":1}","label":3,"position":3,"related_words":null,"sentence_id":"1780608","video_count":1,"view_count":316245,"word":"这是你期待的iPhone17吗","word_cover":{"uri":"tos-cn-p-0015/oATaPIS1RBpQiAqwyo2kP7EAiAqiZI0GTITCs","url_list":["https://p3-sign.douyinpic.com/tos-cn-p-0015/oATaPIS1RBpQiAqwyo2kP7EAiAqiZI0GTITCs~noop.jpeg?lk3s=bfd515bb\u0026x-expires=1722340800\u0026x-signature=TTBnElPNcZNOXUcsnCFsUhRkPpA%3D\u0026from=3218412987","https://p26-sign.douyinpic.com/tos-cn-p-0015/oATaPIS1RBpQiAqwyo2kP7EAiAqiZI0GTITCs~noop.jpeg?lk3s=bfd515bb\u0026x-expires=1722340800\u0026x-signature=8NL%2F2%2FHMHG0m8tUAriri%2FlAQd6c%3D\u0026from=3218412987","https://p11-sign.douyinpic.com/tos-cn-p-0015/oATaPIS1RBpQiAqwyo2kP7EAiAqiZI0GTITCs~noop.jpeg?lk3s=bfd515bb\u0026x-expires=1722340800\u0026x-signature=b5G%2BoJ%2BHjd36O9cNnj8vXqn6CwM%3D\u0026from=3218412987"]},"word_sub_board":null,"word_type":1},{"aweme_infos":null,"can_extend_detail":false,"challenge_id":"","discuss_video_count":0,"display_style":0,"drift_info":null,"event_time":1722218124,"group_id":"7395228752059831603","hot_value":7647038,"hotlist_param":"{\"version\":1}","label":3,"position":4,"related_words":null,"sentence_id":"1779345","video_count":4,"view_count":314100,"word":"为什么湖南成了暴雨中心","word_cover":{"uri":"tos-cn-p-0015/ocNPGNmeZC0ILAL7SBAQ9tICMTBFAlee71XGIW","url_list":["https://p3-sign.douyinpic.com/tos-cn-p-0015/ocNPGNmeZC0ILAL7SBAQ9tICMTBFAlee71XGIW~noop.jpeg?lk3s=bfd515bb\u0026x-expires=1722340800\u0026x-signature=a8eFvDlVMOaR5flr7lEb54gklz8%3D\u0026from=3218412987","https://p26-sign.douyinpic.com/tos-cn-p-0015/ocNPGNmeZC0ILAL7SBAQ9tICMTBFAlee71XGIW~noop.jpeg?lk3s=bfd515bb\u0026x-expires=1722340800\u0026x-signature=jxMlcWHRntI0RTJyLDC3uEPF%2Bdw%3D\u0026from=3218412987","https://p9-sign.douyinpic.com/tos-cn-p-0015/ocNPGNmeZC0ILAL7SBAQ9tICMTBFAlee71XGIW~noop.jpeg?lk3s=bfd515bb\u0026x-expires=1722340800\u0026x-signature=YW4EysiIZaMcDd0mZx36BnUuGNo%3D\u0026from=3218412987"]},"word_sub_board":null,"word_type":1},{"aweme_infos":null,"challenge_id":"","discuss_video_count":0,"display_style":0,"drift_info":null,"event_time":1722295604,"group_id":"7396092702889366825","hot_value":7557500,"hotlist_param":"{\"version\":1}","label":0,"position":5,"related_words":null,"sentence_id":"1780505","video_count":3,"view_count":172810,"word":"多家电商平台调整“仅退款”策略","word_cover":{"uri":"tos-cn-p-0015/oQwiCeyeGBNNLA3BPOIpq9IZTCGQGAyA2M7fUA","url_list":["https://p26-sign.douyinpic.com/tos-cn-p-0015/oQwiCeyeGBNNLA3BPOIpq9IZTCGQGAyA2M7fUA~noop.jpeg?lk3s=bfd515bb\u0026x-expires=1722340800\u0026x-signature=HL2VdYyTgiwVsj7lTBTN6Wvxbso%3D\u0026from=3218412987","https://p3-sign.douyinpic.com/tos-cn-p-0015/oQwiCeyeGBNNLA3BPOIpq9IZTCGQGAyA2M7fUA~noop.jpeg?lk3s=bfd515bb\u0026x-expires=1722340800\u0026x-signature=PWcl%2FS1RhTK0eC69jqa6xWefibo%3D\u0026from=3218412987","https://p9-sign.douyinpic.com/tos-cn-p-0015/oQwiCeyeGBNNLA3BPOIpq9IZTCGQGAyA2M7fUA~noop.jpeg?lk3s=bfd515bb\u0026x-expires=1722340800\u0026x-signature=ULK26LDT0d2JKzm%2F9KyRBKjG32E%3D\u0026from=3218412987"]},"word_sub_board":null,"word_type":1},{"aweme_infos":null,"can_extend_detail":false,"challenge_id":"","discuss_video_count":0,"display_style":0,"drift_info":null,"event_time":1722312072,"group_id":"7394643399779128595","hot_value":7533986,"hotlist_param":"{\"version\":1}","label":1,"position":6,"related_words":null,"sentence_id":"1780779","video_count":2,"view_count":6845375,"word":"奥运开幕式为何引发西方争议","word_cover":{"uri":"tos-cn-p-0015/oczAFEWDgJjBcznFfKm9ADA9IYnbTpQw8RMeHC","url_list":["https://p26-sign.douyinpic.com/tos-cn-p-0015/oczAFEWDgJjBcznFfKm9ADA9IYnbTpQw8RMeHC~noop.jpeg?lk3s=bfd515bb\u0026x-expires=1722340800\u0026x-signature=mBxXsqB4f4IAHKrOVFa1%2BrCj5n4%3D\u0026from=3218412987","https://p3-sign.douyinpic.com/tos-cn-p-0015/oczAFEWDgJjBcznFfKm9ADA9IYnbTpQw8RMeHC~noop.jpeg?lk3s=bfd515bb\u0026x-expires=1722340800\u0026x-signature=JRRrkBMAEr40O69tTfFr%2F0P6yGg%3D\u0026from=3218412987","https://p11-sign.douyinpic.com/tos-cn-p-0015/oczAFEWDgJjBcznFfKm9ADA9IYnbTpQw8RMeHC~noop.jpeg?lk3s=bfd515bb\u0026x-expires=1722340800\u0026x-signature=fDiz5TOtbkaGEg%2FIppKJOPWS44g%3D\u0026from=3218412987"]},"word_sub_board":null,"word_type":1},{"aweme_infos":null,"can_extend_detail":false,"challenge_id":"","display_style":0,"drift_info":null,"event_time":1722238919,"group_id":"7395891963382682907","hot_value":5486869,"hotlist_param":"{\"version\":1}","label":0,"position":7,"related_words":null,"sentence_id":"1779824","video_count":3,"view_count":1056942,"word":"起底实习内推灰产","word_cover":{"uri":"tos-cn-p-0015/oEwP6WAMunBIPIQMLmWYmiEyEEmqFiIZAcBw1","url_list":["https://p3-sign.douyinpic.com/tos-cn-p-0015/oEwP6WAMunBIPIQMLmWYmiEyEEmqFiIZAcBw1~noop.jpeg?lk3s=bfd515bb\u0026x-expires=1722340800\u0026x-signature=L0JuSjgkRvtYGntS8kA2iGl9Ync%3D\u0026from=3218412987","https://p11-sign.douyinpic.com/tos-cn-p-0015/oEwP6WAMunBIPIQMLmWYmiEyEEmqFiIZAcBw1~noop.jpeg?lk3s=bfd515bb\u0026x-expires=1722340800\u0026x-signature=sHE5jeaRvpZN5G4rXDcnmM%2BgcQA%3D\u0026from=3218412987","https://p26-sign.douyinpic.com/tos-cn-p-0015/oEwP6WAMunBIPIQMLmWYmiEyEEmqFiIZAcBw1~noop.jpeg?lk3s=bfd515bb\u0026x-expires=1722340800\u0026x-signature=iCkPLwWdvQiVJKvIyiR1AkZ4Ngs%3D\u0026from=3218412987"]},"word_sub_board":null,"word_type":1},{"aweme_infos":null,"challenge_id":"","discuss_video_count":0,"display_style":0,"drift_info":null,"event_time":1722237664,"group_id":"7395121507737867535","hot_value":5260746,"hotlist_param":"{\"version\":1}","label":0,"position":8,"related_words":null,"sentence_id":"1779846","video_count":3,"view_count":541315,"word":"薛之谦演唱会观众激动亲吻镜头","word_cover":{"uri":"tos-cn-p-0015/oAI7XBCDmBTkh7LFE5ekcAIGAACmfpMgM9QvSU","url_list":["https://p11-sign.douyinpic.com/tos-cn-p-0015/oAI7XBCDmBTkh7LFE5ekcAIGAACmfpMgM9QvSU~noop.jpeg?lk3s=bfd515bb\u0026x-expires=1722340800\u0026x-signature=qS3sdCKOWNr4UsxKEUGhNs2NQ98%3D\u0026from=3218412987","https://p3-sign.douyinpic.com/tos-cn-p-0015/oAI7XBCDmBTkh7LFE5ekcAIGAACmfpMgM9QvSU~noop.jpeg?lk3s=bfd515bb\u0026x-expires=1722340800\u0026x-signature=ZKqFfmKpf4m4%2BhK5SO1HLwUTYOk%3D\u0026from=3218412987","https://p26-sign.douyinpic.com/tos-cn-p-0015/oAI7XBCDmBTkh7LFE5ekcAIGAACmfpMgM9QvSU~noop.jpeg?lk3s=bfd515bb\u0026x-expires=1722340800\u0026x-signature=0YL4Rguy3thLjx1wth28idfADGU%3D\u0026from=3218412987"]},"word_sub_board":null,"word_type":1},{"aweme_infos":null,"can_extend_detail":false,"challenge_id":"","display_style":0,"drift_info":null,"event_time":1722235492,"group_id":"7395883636682413331","hot_value":5232120,"hotlist_param":"{\"version\":1}","label":0,"position":9,"related_words":null,"sentence_id":"1779774","video_count":2,"view_count":1712208,"word":"辽宁鸭绿江水位上涨沿江街道被淹","word_cover":{"uri":"tos-cn-p-0015/oAiTEQXBIPBnBiqwPIOScAIAZVPI0F4CBiQ6I","url_list":["https://p3-sign.douyinpic.com/tos-cn-p-0015/oAiTEQXBIPBnBiqwPIOScAIAZVPI0F4CBiQ6I~noop.jpeg?lk3s=bfd515bb\u0026x-expires=1722340800\u0026x-signature=Wx8HYEXpdmMdcPR8dVe6%2Fv4eG6E%3D\u0026from=3218412987","https://p11-sign.douyinpic.com/tos-cn-p-0015/oAiTEQXBIPBnBiqwPIOScAIAZVPI0F4CBiQ6I~noop.jpeg?lk3s=bfd515bb\u0026x-expires=1722340800\u0026x-signature=DiCUd3J34fN0znftamy53oh9j2w%3D\u0026from=3218412987","https://p26-sign.douyinpic.com/tos-cn-p-0015/oAiTEQXBIPBnBiqwPIOScAIAZVPI0F4CBiQ6I~noop.jpeg?lk3s=bfd515bb\u0026x-expires=1722340800\u0026x-signature=THfZ1C1laODcOB1%2F9WvUGtm0ufo%3D\u0026from=3218412987"]},"word_sub_board":null,"word_type":1},{"aweme_infos":null,"challenge_id":"","display_style":0,"drift_info":null,"event_time":1722236669,"group_id":"7394364713318274343","hot_value":5182177,"hotlist_param":"{\"version\":1}","label":0,"position":10,"related_words":null,"sentence_id":"1779808","video_count":1,"view_count":633201,"word":"法国人看上了中国记者的拍摄设备","word_cover":{"uri":"tos-cn-p-0015/oQ1OHBeIeATeNRIEjgCk7HArU4gyLEBBGJan8c","url_list":["https://p26-sign.douyinpic.com/tos-cn-p-0015/oQ1OHBeIeATeNRIEjgCk7HArU4gyLEBBGJan8c~noop.jpeg?lk3s=bfd515bb\u0026x-expires=1722340800\u0026x-signature=gJLbkfT9yhRAegbO5oYWhsYZtmc%3D\u0026from=3218412987","https://p3-sign.douyinpic.com/tos-cn-p-0015/oQ1OHBeIeATeNRIEjgCk7HArU4gyLEBBGJan8c~noop.jpeg?lk3s=bfd515bb\u0026x-expires=1722340800\u0026x-signature=rJ%2B6fDKakro4JNXAqpK5bmBf7GE%3D\u0026from=3218412987","https://p11-sign.douyinpic.com/tos-cn-p-0015/oQ1OHBeIeATeNRIEjgCk7HArU4gyLEBBGJan8c~noop.jpeg?lk3s=bfd515bb\u0026x-expires=1722340800\u0026x-signature=JHx6itrM0lbWR3FkWKRg50YyYFw%3D\u0026from=3218412987"]},"word_sub_board":null,"word_type":1},{"aweme_infos":null,"can_extend_detail":false,"challenge_id":"","display_style":0,"drift_info":null,"event_time":1722237488,"group_id":"7395886626808943913","hot_value":5167229,"hotlist_param":"{\"version\":1}","label":0,"position":11,"related_words":null,"sentence_id":"1779819","video_count":1,"view_count":2079329,"word":"警方回应蓉城与浙江球迷起冲突","word_cover":{"uri":"tos-cn-p-0015/owBAM6Fp8IDbZxDAEOzgfhEFmnQu9RNACeRyIB","url_list":["https://p3-sign.douyinpic.com/tos-cn-p-0015/owBAM6Fp8IDbZxDAEOzgfhEFmnQu9RNACeRyIB~noop.jpeg?lk3s=bfd515bb\u0026x-expires=1722340800\u0026x-signature=zA46qs2eHVEKG515MN1JKvjlIBo%3D\u0026from=3218412987","https://p26-sign.douyinpic.com/tos-cn-p-0015/owBAM6Fp8IDbZxDAEOzgfhEFmnQu9RNACeRyIB~noop.jpeg?lk3s=bfd515bb\u0026x-expires=1722340800\u0026x-signature=5qm7xCO3JkSlVkzQYcnPpjcfhXQ%3D\u0026from=3218412987","https://p11-sign.douyinpic.com/tos-cn-p-0015/owBAM6Fp8IDbZxDAEOzgfhEFmnQu9RNACeRyIB~noop.jpeg?lk3s=bfd515bb\u0026x-expires=1722340800\u0026x-signature=j9Gmi2Y%2FxteM7X5kWsh01dnNgVU%3D\u0026from=3218412987"]},"word_sub_board":null,"word_type":1},{"aweme_infos":null,"challenge_id":"","discuss_video_count":0,"display_style":0,"drift_info":null,"event_time":1722241444,"group_id":"7395371141345056052","hot_value":5121173,"hotlist_param":"{\"version\":1}","label":0,"position":12,"related_words":null,"sentence_id":"1779915","video_count":1,"view_count":731535,"word":"苹果将部分产能迁回中国意味什么","word_cover":{"uri":"tos-cn-p-0015/oURmpDDDIABEkVusfAAgQykFr0OleaK8omB9Cn","url_list":["https://p26-sign.douyinpic.com/tos-cn-p-0015/oURmpDDDIABEkVusfAAgQykFr0OleaK8omB9Cn~noop.jpeg?lk3s=bfd515bb\u0026x-expires=1722340800\u0026x-signature=OGHdceNdEVrPj9gzWbpGtvSpJf4%3D\u0026from=3218412987","https://p3-sign.douyinpic.com/tos-cn-p-0015/oURmpDDDIABEkVusfAAgQykFr0OleaK8omB9Cn~noop.jpeg?lk3s=bfd515bb\u0026x-expires=1722340800\u0026x-signature=zLhXyBfPR7snmyksvfIFpkrCUtY%3D\u0026from=3218412987","https://p9-sign.douyinpic.com/tos-cn-p-0015/oURmpDDDIABEkVusfAAgQykFr0OleaK8omB9Cn~noop.jpeg?lk3s=bfd515bb\u0026x-expires=1722340800\u0026x-signature=dop5Df5b7j9fEa0vNqOx8TWQkeo%3D\u0026from=3218412987"]},"word_sub_board":null,"word_type":1},{"aweme_infos":null,"can_extend_detail":false,"challenge_id":"","display_style":0,"drift_info":null,"event_time":1722312815,"group_id":"7395894488772695322","hot_value":5029627,"hotlist_param":"{\"version\":1}","label":0,"position":13,"related_words":null,"sentence_id":"1780811","video_count":2,"view_count":1226086,"word":"宣传部回应学生玩梗被赶下台","word_cover":{"uri":"tos-cn-p-0015/oYMuUZiPo3r8EaAukwQIAqQQMBqhIUJbiBAqv","url_list":["https://p3-sign.douyinpic.com/tos-cn-p-0015/oYMuUZiPo3r8EaAukwQIAqQQMBqhIUJbiBAqv~noop.jpeg?lk3s=bfd515bb\u0026x-expires=1722340800\u0026x-signature=fG4uacLUCO0lInvJeliO86SY1Ww%3D\u0026from=3218412987","https://p26-sign.douyinpic.com/tos-cn-p-0015/oYMuUZiPo3r8EaAukwQIAqQQMBqhIUJbiBAqv~noop.jpeg?lk3s=bfd515bb\u0026x-expires=1722340800\u0026x-signature=usP5%2BS9HNEVOO6En%2BKnJF4k1fv4%3D\u0026from=3218412987","https://p11-sign.douyinpic.com/tos-cn-p-0015/oYMuUZiPo3r8EaAukwQIAqQQMBqhIUJbiBAqv~noop.jpeg?lk3s=bfd515bb\u0026x-expires=1722340800\u0026x-signature=%2B9cEYYVdtU3e%2FJJT9%2Fyp5lpRu0I%3D\u0026from=3218412987"]},"word_sub_board":null,"word_type":1},{"aweme_infos":null,"can_extend_detail":false,"challenge_id":"","discuss_video_count":0,"display_style":0,"drift_info":null,"event_time":1722303124,"group_id":"7395520287049438479","hot_value":5020200,"hotlist_param":"{\"version\":1}","label":3,"position":14,"related_words":null,"sentence_id":"1780570","video_count":3,"view_count":382160,"word":"湖南资兴暴雨已致4死3失踪","word_cover":{"uri":"tos-cn-p-0015/oQtIfhSAQzYBaLUCnQfGeBc7QBALEOIACOLNQB","url_list":["https://p9-sign.douyinpic.com/tos-cn-p-0015/oQtIfhSAQzYBaLUCnQfGeBc7QBALEOIACOLNQB~noop.jpeg?lk3s=bfd515bb\u0026x-expires=1722340800\u0026x-signature=GKhGyvl1ntkDtMoyOsEigRGq16M%3D\u0026from=3218412987","https://p26-sign.douyinpic.com/tos-cn-p-0015/oQtIfhSAQzYBaLUCnQfGeBc7QBALEOIACOLNQB~noop.jpeg?lk3s=bfd515bb\u0026x-expires=1722340800\u0026x-signature=xUMszuXBS11s9UufPhMX%2BOwDDCI%3D\u0026from=3218412987","https://p3-sign.douyinpic.com/tos-cn-p-0015/oQtIfhSAQzYBaLUCnQfGeBc7QBALEOIACOLNQB~noop.jpeg?lk3s=bfd515bb\u0026x-expires=1722340800\u0026x-signature=BBe9f52dQ7gQmxyvohtcnkNCnYw%3D\u0026from=3218412987"]},"word_sub_board":null,"word_type":1},{"aweme_infos":null,"can_extend_detail":false,"challenge_id":"","discuss_video_count":0,"display_style":0,"drift_info":null,"event_time":1722236658,"group_id":"7395915614407415040","hot_value":5018125,"hotlist_param":"{\"version\":1}","label":0,"position":15,"related_words":null,"sentence_id":"1779779","video_count":2,"view_count":1721465,"word":"女正部李微微被查","word_cover":{"uri":"tos-cn-p-0015/osCqAfPTfWUs0BngBNQMZk8RA1fWA63DBE5DH7","url_list":["https://p3-sign.douyinpic.com/tos-cn-p-0015/osCqAfPTfWUs0BngBNQMZk8RA1fWA63DBE5DH7~noop.jpeg?lk3s=bfd515bb\u0026x-expires=1722340800\u0026x-signature=0EZIG56BljLIuWvjd2yN8eFTZKU%3D\u0026from=3218412987","https://p11-sign.douyinpic.com/tos-cn-p-0015/osCqAfPTfWUs0BngBNQMZk8RA1fWA63DBE5DH7~noop.jpeg?lk3s=bfd515bb\u0026x-expires=1722340800\u0026x-signature=cGg8KQt%2BQLwk2QrPx2csc%2Bmh9L8%3D\u0026from=3218412987","https://p26-sign.douyinpic.com/tos-cn-p-0015/osCqAfPTfWUs0BngBNQMZk8RA1fWA63DBE5DH7~noop.jpeg?lk3s=bfd515bb\u0026x-expires=1722340800\u0026x-signature=LqJzZiKWD8x5t29jibw0P80564Y%3D\u0026from=3218412987"]},"word_sub_board":null,"word_type":1},{"aweme_infos":null,"challenge_id":"","display_style":0,"drift_info":null,"event_time":1722252537,"group_id":"7395587141092922639","hot_value":4967330,"hotlist_param":"{\"version\":1}","label":0,"position":16,"related_words":null,"sentence_id":"1780198","video_count":3,"view_count":2643940,"word":"今年已有7名正部级被查","word_cover":{"uri":"tos-cn-p-0015/okIBnFNYuCG1BhDOIfVSVEFAEudP4TeevStA7h","url_list":["https://p3-sign.douyinpic.com/tos-cn-p-0015/okIBnFNYuCG1BhDOIfVSVEFAEudP4TeevStA7h~noop.jpeg?lk3s=bfd515bb\u0026x-expires=1722340800\u0026x-signature=RlXXbnT2G%2FU9yxlWR1rFnLCnJ%2F8%3D\u0026from=3218412987","https://p11-sign.douyinpic.com/tos-cn-p-0015/okIBnFNYuCG1BhDOIfVSVEFAEudP4TeevStA7h~noop.jpeg?lk3s=bfd515bb\u0026x-expires=1722340800\u0026x-signature=MdygXQwslXF%2BIqfASPtuXUoe81w%3D\u0026from=3218412987","https://p26-sign.douyinpic.com/tos-cn-p-0015/okIBnFNYuCG1BhDOIfVSVEFAEudP4TeevStA7h~noop.jpeg?lk3s=bfd515bb\u0026x-expires=1722340800\u0026x-signature=YqllNlvrvltsWKL8RDqdqoOVTck%3D\u0026from=3218412987"]},"word_sub_board":null,"word_type":1},{"aweme_infos":null,"can_extend_detail":false,"challenge_id":"","discuss_video_count":0,"display_style":0,"drift_info":null,"event_time":1722246747,"group_id":"7395891166484649243","hot_value":4919632,"hotlist_param":"{\"version\":1}","label":0,"position":17,"related_words":null,"sentence_id":"1780032","video_count":3,"view_count":1867910,"word":"官方通报清华毕业生举报局长贪腐","word_cover":{"uri":"tos-cn-p-0015/oIVfE4CNBAnIAu7GSIWFeBYAnb6GTLSCtafa9B","url_list":["https://p3-sign.douyinpic.com/tos-cn-p-0015/oIVfE4CNBAnIAu7GSIWFeBYAnb6GTLSCtafa9B~noop.jpeg?lk3s=bfd515bb\u0026x-expires=1722340800\u0026x-signature=9l8WznDTEeH3HfkvMSbibvQOWw4%3D\u0026from=3218412987","https://p11-sign.douyinpic.com/tos-cn-p-0015/oIVfE4CNBAnIAu7GSIWFeBYAnb6GTLSCtafa9B~noop.jpeg?lk3s=bfd515bb\u0026x-expires=1722340800\u0026x-signature=%2Fqxq6ZAvRNV9Awp0po2y98W%2FCRU%3D\u0026from=3218412987","https://p26-sign.douyinpic.com/tos-cn-p-0015/oIVfE4CNBAnIAu7GSIWFeBYAnb6GTLSCtafa9B~noop.jpeg?lk3s=bfd515bb\u0026x-expires=1722340800\u0026x-signature=H8dP4b7lVMdW1zm6sR29TMtMpwA%3D\u0026from=3218412987"]},"word_sub_board":null,"word_type":1},{"aweme_infos":null,"can_extend_detail":false,"challenge_id":"","display_style":0,"drift_info":null,"event_time":1722171213,"group_id":"7394976701098693915","hot_value":4917593,"hotlist_param":"{\"version\":1}","label":0,"position":18,"related_words":null,"sentence_id":"1779115","video_count":24,"view_count":1148725,"word":"抗癌博主大飞去世","word_cover":{"uri":"tos-cn-p-0015/oMUIGiPyZC0IRrXIYxXQDqPgSAZ5qmpRKoAiB","url_list":["https://p26-sign.douyinpic.com/tos-cn-p-0015/oMUIGiPyZC0IRrXIYxXQDqPgSAZ5qmpRKoAiB~noop.jpeg?lk3s=bfd515bb\u0026x-expires=1722340800\u0026x-signature=4FlZjM71lsLRWn95r4tATUarB28%3D\u0026from=3218412987","https://p3-sign.douyinpic.com/tos-cn-p-0015/oMUIGiPyZC0IRrXIYxXQDqPgSAZ5qmpRKoAiB~noop.jpeg?lk3s=bfd515bb\u0026x-expires=1722340800\u0026x-signature=zaEOmg2f50j1%2BVvIwJqoDU%2FjteY%3D\u0026from=3218412987","https://p11-sign.douyinpic.com/tos-cn-p-0015/oMUIGiPyZC0IRrXIYxXQDqPgSAZ5qmpRKoAiB~noop.jpeg?lk3s=bfd515bb\u0026x-expires=1722340800\u0026x-signature=LGmbdhzMJT1Dsh%2FNvh5U5mA6GZA%3D\u0026from=3218412987"]},"word_sub_board":null,"word_type":1},{"aweme_infos":null,"challenge_id":"","display_style":0,"drift_info":null,"event_time":1722251636,"group_id":"7394827140116501799","hot_value":4903130,"hotlist_param":"{\"version\":1}","label":0,"position":19,"related_words":null,"sentence_id":"1780116","video_count":3,"view_count":1167582,"word":"卡塔尔王室在法国遭窃","word_cover":{"uri":"tos-cn-p-0015/o48TID8bUDANNMFdbzF6A9mDeA5g0BapQFf0nE","url_list":["https://p3-sign.douyinpic.com/tos-cn-p-0015/o48TID8bUDANNMFdbzF6A9mDeA5g0BapQFf0nE~noop.jpeg?lk3s=bfd515bb\u0026x-expires=1722340800\u0026x-signature=PeU807ngO8Vx4lWBoDnA%2B4sbzH8%3D\u0026from=3218412987","https://p26-sign.douyinpic.com/tos-cn-p-0015/o48TID8bUDANNMFdbzF6A9mDeA5g0BapQFf0nE~noop.jpeg?lk3s=bfd515bb\u0026x-expires=1722340800\u0026x-signature=%2BnXF8L1kY7uSCZtgSuSMt4subgw%3D\u0026from=3218412987","https://p9-sign.douyinpic.com/tos-cn-p-0015/o48TID8bUDANNMFdbzF6A9mDeA5g0BapQFf0nE~noop.jpeg?lk3s=bfd515bb\u0026x-expires=1722340800\u0026x-signature=OMwRWku7cVoDOvtcbJM9qYEwx4g%3D\u0026from=3218412987"]},"word_sub_board":null,"word_type":1},{"aweme_infos":null,"can_extend_detail":false,"challenge_id":"","display_style":0,"drift_info":null,"event_time":1722238120,"group_id":"7395840930287211830","hot_value":4868976,"hotlist_param":"{\"version\":1}","label":0,"position":20,"related_words":null,"sentence_id":"1779854","video_count":3,"view_count":385875,"word":"况盛回应争议事件","word_cover":{"uri":"tos-cn-p-0015/okXznADl0CB5yEImKpFfABg1MQnFDeEA9sDwAM","url_list":["https://p26-sign.douyinpic.com/tos-cn-p-0015/okXznADl0CB5yEImKpFfABg1MQnFDeEA9sDwAM~noop.jpeg?lk3s=bfd515bb\u0026x-expires=1722340800\u0026x-signature=Njv87I1CF9M1S%2FGNv2wYTAAsB4w%3D\u0026from=3218412987","https://p9-sign.douyinpic.com/tos-cn-p-0015/okXznADl0CB5yEImKpFfABg1MQnFDeEA9sDwAM~noop.jpeg?lk3s=bfd515bb\u0026x-expires=1722340800\u0026x-signature=hDsql1NYBazR01o4W38YfBZXKkY%3D\u0026from=3218412987","https://p3-sign.douyinpic.com/tos-cn-p-0015/okXznADl0CB5yEImKpFfABg1MQnFDeEA9sDwAM~noop.jpeg?lk3s=bfd515bb\u0026x-expires=1722340800\u0026x-signature=U44LNp7aL6HQjtXXoNN%2F92e%2FAUQ%3D\u0026from=3218412987"]},"word_sub_board":null,"word_type":1},{"aweme_infos":null,"can_extend_detail":false,"challenge_id":"","discuss_video_count":0,"display_style":0,"drift_info":null,"event_time":1722313075,"group_id":"7395843237921527081","hot_value":4841887,"hotlist_param":"{\"version\":1}","label":1,"position":21,"related_words":null,"sentence_id":"1780817","video_count":5,"view_count":842492,"word":"多部门调拨1.5万件救灾物资援湘","word_cover":{"uri":"tos-cn-p-0015/oIfeEApnO5Rsyqam1oBUI1p9gBiKAzA3UoBDUi","url_list":["https://p3-sign.douyinpic.com/tos-cn-p-0015/oIfeEApnO5Rsyqam1oBUI1p9gBiKAzA3UoBDUi~noop.jpeg?lk3s=bfd515bb\u0026x-expires=1722340800\u0026x-signature=6tbcP4%2Bys9IRodGR%2B3BH4uWdi88%3D\u0026from=3218412987","https://p11-sign.douyinpic.com/tos-cn-p-0015/oIfeEApnO5Rsyqam1oBUI1p9gBiKAzA3UoBDUi~noop.jpeg?lk3s=bfd515bb\u0026x-expires=1722340800\u0026x-signature=UebnXqPpgnuP%2FrftF7FetjaCJjc%3D\u0026from=3218412987","https://p9-sign.douyinpic.com/tos-cn-p-0015/oIfeEApnO5Rsyqam1oBUI1p9gBiKAzA3UoBDUi~noop.jpeg?lk3s=bfd515bb\u0026x-expires=1722340800\u0026x-signature=tCuLcjSP%2F3%2F03otoPD2gjg6COu0%3D\u0026from=3218412987"]},"word_sub_board":null,"word_type":1},{"aweme_infos":null,"can_extend_detail":false,"challenge_id":"","display_style":0,"drift_info":null,"event_time":1722252185,"group_id":"7396598245273670963","hot_value":4713351,"hotlist_param":"{\"version\":1}","label":0,"position":22,"related_words":null,"sentence_id":"1780136","video_count":5,"view_count":962210,"word":"黄雨婷班主任称没给她布置作业","word_cover":{"uri":"tos-cn-p-0015/oEGsECEDEJfArg1CWm1nA8fIxRFR89ApdNBHng","url_list":["https://p3-sign.douyinpic.com/tos-cn-p-0015/oEGsECEDEJfArg1CWm1nA8fIxRFR89ApdNBHng~noop.jpeg?lk3s=bfd515bb\u0026x-expires=1722340800\u0026x-signature=Re4LfhNze%2FPwnam6BIGd91dHWZ4%3D\u0026from=3218412987","https://p26-sign.douyinpic.com/tos-cn-p-0015/oEGsECEDEJfArg1CWm1nA8fIxRFR89ApdNBHng~noop.jpeg?lk3s=bfd515bb\u0026x-expires=1722340800\u0026x-signature=PaMD0Uo6cfHtSKyNXYLybEciVIY%3D\u0026from=3218412987","https://p11-sign.douyinpic.com/tos-cn-p-0015/oEGsECEDEJfArg1CWm1nA8fIxRFR89ApdNBHng~noop.jpeg?lk3s=bfd515bb\u0026x-expires=1722340800\u0026x-signature=HXylSspcs%2FH8WjxZTAFHDJaiiEk%3D\u0026from=3218412987"]},"word_sub_board":null,"word_type":1},{"aweme_infos":null,"can_extend_detail":false,"challenge_id":"","display_style":0,"drift_info":null,"event_time":1722245892,"group_id":"7395237143276852514","hot_value":4702213,"hotlist_param":"{\"version\":1}","label":0,"position":23,"related_words":null,"sentence_id":"1780016","video_count":1,"view_count":293695,"word":"哈里斯称面对特朗普自己是弱势方","word_cover":{"uri":"tos-cn-p-0015/oYcTGetJBIDaQxVfVCNALCwOIf7lAXRCNBNbmL","url_list":["https://p3-sign.douyinpic.com/tos-cn-p-0015/oYcTGetJBIDaQxVfVCNALCwOIf7lAXRCNBNbmL~noop.jpeg?lk3s=bfd515bb\u0026x-expires=1722340800\u0026x-signature=S2Ga%2BBVEEtvwF5uh8%2FNZUuFk%2B3Q%3D\u0026from=3218412987","https://p26-sign.douyinpic.com/tos-cn-p-0015/oYcTGetJBIDaQxVfVCNALCwOIf7lAXRCNBNbmL~noop.jpeg?lk3s=bfd515bb\u0026x-expires=1722340800\u0026x-signature=uRopxv7m2UCTRskkudMqgxek8BU%3D\u0026from=3218412987","https://p11-sign.douyinpic.com/tos-cn-p-0015/oYcTGetJBIDaQxVfVCNALCwOIf7lAXRCNBNbmL~noop.jpeg?lk3s=bfd515bb\u0026x-expires=1722340800\u0026x-signature=Mbi8sPtb9LQssuit89Li1uRWO4w%3D\u0026from=3218412987"]},"word_sub_board":null,"word_type":1},{"aweme_infos":null,"challenge_id":"","display_style":0,"drift_info":null,"event_time":1722235449,"group_id":"7395155498281522483","hot_value":4680002,"hotlist_param":"{\"version\":1}","label":0,"position":24,"related_words":null,"sentence_id":"1779778","video_count":1,"view_count":989549,"word":"武大拟对3名研究生作退学处理","word_cover":{"uri":"tos-cn-p-0015/osNTqnQqg1lsCbtBQtvchBAfH7Le3EesvANGVI","url_list":["https://p11-sign.douyinpic.com/tos-cn-p-0015/osNTqnQqg1lsCbtBQtvchBAfH7Le3EesvANGVI~noop.jpeg?lk3s=bfd515bb\u0026x-expires=1722340800\u0026x-signature=88LbPTutx8uODFFDhAEQ6%2BbIJes%3D\u0026from=3218412987","https://p3-sign.douyinpic.com/tos-cn-p-0015/osNTqnQqg1lsCbtBQtvchBAfH7Le3EesvANGVI~noop.jpeg?lk3s=bfd515bb\u0026x-expires=1722340800\u0026x-signature=Gdpg06P9WzxnAWu063gDr2eHHE8%3D\u0026from=3218412987","https://p26-sign.douyinpic.com/tos-cn-p-0015/osNTqnQqg1lsCbtBQtvchBAfH7Le3EesvANGVI~noop.jpeg?lk3s=bfd515bb\u0026x-expires=1722340800\u0026x-signature=ls45SQ3YgbQwGYVFLomxwPSfX%2FA%3D\u0026from=3218412987"]},"word_sub_board":null,"word_type":1},{"aweme_infos":null,"can_extend_detail":false,"challenge_id":"","display_style":0,"drift_info":null,"event_time":1722260613,"group_id":"7395893800097404194","hot_value":4670281,"hotlist_param":"{\"version\":1}","label":0,"position":25,"related_words":null,"sentence_id":"1780336","video_count":2,"view_count":277358,"word":"吉林临江市区洪水倒灌","word_cover":{"uri":"tos-cn-p-0015/oQs97pESvPaShnCkAu40TLgEDfAqFABfrBvm0I","url_list":["https://p3-sign.douyinpic.com/tos-cn-p-0015/oQs97pESvPaShnCkAu40TLgEDfAqFABfrBvm0I~noop.jpeg?lk3s=bfd515bb\u0026x-expires=1722340800\u0026x-signature=68lea8a0Y%2BnSxPdXBG6bQpaEYlA%3D\u0026from=3218412987","https://p11-sign.douyinpic.com/tos-cn-p-0015/oQs97pESvPaShnCkAu40TLgEDfAqFABfrBvm0I~noop.jpeg?lk3s=bfd515bb\u0026x-expires=1722340800\u0026x-signature=gvxD9yUJoHc8IeNsUe227%2B5DmfU%3D\u0026from=3218412987","https://p26-sign.douyinpic.com/tos-cn-p-0015/oQs97pESvPaShnCkAu40TLgEDfAqFABfrBvm0I~noop.jpeg?lk3s=bfd515bb\u0026x-expires=1722340800\u0026x-signature=gkuQxS62jzzOMld8RsjqI1TVUUI%3D\u0026from=3218412987"]},"word_sub_board":null,"word_type":1},{"aweme_infos":null,"can_extend_detail":false,"challenge_id":"","display_style":0,"drift_info":null,"event_time":1722236959,"group_id":"7395915332802286848","hot_value":4624552,"hotlist_param":"{\"version\":1}","label":0,"position":26,"related_words":null,"sentence_id":"1779835","video_count":1,"view_count":903750,"word":"园方回应小海狮已救活","word_cover":{"uri":"tos-cn-p-0015/oEyIgi8EeAaIzAIfnR9US5BR7rxBABiBDFJAjS","url_list":["https://p26-sign.douyinpic.com/tos-cn-p-0015/oEyIgi8EeAaIzAIfnR9US5BR7rxBABiBDFJAjS~noop.jpeg?lk3s=bfd515bb\u0026x-expires=1722340800\u0026x-signature=wMrjEfu%2FLB2s7xkZaTxU8ARvJFw%3D\u0026from=3218412987","https://p3-sign.douyinpic.com/tos-cn-p-0015/oEyIgi8EeAaIzAIfnR9US5BR7rxBABiBDFJAjS~noop.jpeg?lk3s=bfd515bb\u0026x-expires=1722340800\u0026x-signature=8qh0u%2BfNWp0Jo%2FF%2FeBUffOqFPm0%3D\u0026from=3218412987","https://p11-sign.douyinpic.com/tos-cn-p-0015/oEyIgi8EeAaIzAIfnR9US5BR7rxBABiBDFJAjS~noop.jpeg?lk3s=bfd515bb\u0026x-expires=1722340800\u0026x-signature=GYw4Hww4iSIf4to8vlaK5Kn2j38%3D\u0026from=3218412987"]},"word_sub_board":null,"word_type":1},{"aweme_infos":null,"challenge_id":"","display_style":0,"drift_info":null,"event_time":1722254011,"group_id":"7394052283011290422","hot_value":4609918,"hotlist_param":"{\"version\":1}","label":0,"position":27,"related_words":null,"sentence_id":"1780193","video_count":1,"view_count":3099717,"word":"230斤小伙骑共享电单车被断电","word_cover":{"uri":"tos-cn-p-0015/o8FttnBmpAesAmWHEwn119tBNDOfQMCPAQ0gQD","url_list":["https://p3-sign.douyinpic.com/tos-cn-p-0015/o8FttnBmpAesAmWHEwn119tBNDOfQMCPAQ0gQD~noop.jpeg?lk3s=bfd515bb\u0026x-expires=1722340800\u0026x-signature=TxYtgYQ9P6BAR0Whkqx7Cvjlk4g%3D\u0026from=3218412987","https://p26-sign.douyinpic.com/tos-cn-p-0015/o8FttnBmpAesAmWHEwn119tBNDOfQMCPAQ0gQD~noop.jpeg?lk3s=bfd515bb\u0026x-expires=1722340800\u0026x-signature=wkc6GETpyt0lTg12GjuE%2BdeTwnU%3D\u0026from=3218412987","https://p11-sign.douyinpic.com/tos-cn-p-0015/o8FttnBmpAesAmWHEwn119tBNDOfQMCPAQ0gQD~noop.jpeg?lk3s=bfd515bb\u0026x-expires=1722340800\u0026x-signature=YmXxPrNiq4GkiXsmOsg7Vim20Jc%3D\u0026from=3218412987"]},"word_sub_board":null,"word_type":1},{"aweme_infos":null,"challenge_id":"","display_style":0,"drift_info":null,"event_time":1722310984,"group_id":"7395892040124650802","hot_value":4608784,"hotlist_param":"{\"version\":1}","label":0,"position":28,"related_words":null,"sentence_id":"1780750","video_count":1,"view_count":349114,"word":"官方通报男子高铁上霸座充电","word_cover":{"uri":"tos-cn-p-0015/oA7NTCGpIBCI1eRMeBAAQlyLP0nvGGfDHi57Go","url_list":["https://p3-sign.douyinpic.com/tos-cn-p-0015/oA7NTCGpIBCI1eRMeBAAQlyLP0nvGGfDHi57Go~noop.jpeg?lk3s=bfd515bb\u0026x-expires=1722340800\u0026x-signature=QfBH6sUnzAIwHEsRehgEaVre%2FqU%3D\u0026from=3218412987","https://p26-sign.douyinpic.com/tos-cn-p-0015/oA7NTCGpIBCI1eRMeBAAQlyLP0nvGGfDHi57Go~noop.jpeg?lk3s=bfd515bb\u0026x-expires=1722340800\u0026x-signature=2e6TbZ4pmlRXTkS5X6US%2BTZmIOw%3D\u0026from=3218412987","https://p11-sign.douyinpic.com/tos-cn-p-0015/oA7NTCGpIBCI1eRMeBAAQlyLP0nvGGfDHi57Go~noop.jpeg?lk3s=bfd515bb\u0026x-expires=1722340800\u0026x-signature=5RY9MC%2FF9G2W42ZomC9eNKOdGdg%3D\u0026from=3218412987"]},"word_sub_board":null,"word_type":1},{"aweme_infos":null,"challenge_id":"","display_style":0,"drift_info":null,"event_time":1722266326,"group_id":"7395383100698744116","hot_value":4599291,"hotlist_param":"{\"version\":1}","label":0,"position":29,"related_words":null,"sentence_id":"1780438","video_count":1,"view_count":533570,"word":"美民调：特朗普支持率下滑至36%","word_cover":{"uri":"tos-cn-p-0015/oQg9ypES2qPnZnDWAIFgkXgIDfAFFAB8uBem5Q","url_list":["https://p3-sign.douyinpic.com/tos-cn-p-0015/oQg9ypES2qPnZnDWAIFgkXgIDfAFFAB8uBem5Q~noop.jpeg?lk3s=bfd515bb\u0026x-expires=1722340800\u0026x-signature=DCb39cZfjjHyQWOnDYdTlulUjhc%3D\u0026from=3218412987","https://p9-sign.douyinpic.com/tos-cn-p-0015/oQg9ypES2qPnZnDWAIFgkXgIDfAFFAB8uBem5Q~noop.jpeg?lk3s=bfd515bb\u0026x-expires=1722340800\u0026x-signature=Bg9rKEG43hxwCuCc5NjcLO8icpQ%3D\u0026from=3218412987","https://p26-sign.douyinpic.com/tos-cn-p-0015/oQg9ypES2qPnZnDWAIFgkXgIDfAFFAB8uBem5Q~noop.jpeg?lk3s=bfd515bb\u0026x-expires=1722340800\u0026x-signature=4qCaEdVJ4dvLsrI8N9IWIyHXbf0%3D\u0026from=3218412987"]},"word_sub_board":null,"word_type":1},{"aweme_infos":null,"can_extend_detail":false,"challenge_id":"","display_style":0,"drift_info":null,"event_time":1722238386,"group_id":"7394352640035345675","hot_value":4579405,"hotlist_param":"{\"version\":1}","label":0,"position":30,"related_words":null,"sentence_id":"1779807","video_count":1,"view_count":455526,"word":"特朗普感谢马斯克对自己的支持","word_cover":{"uri":"tos-cn-p-0015/oo4PsWKEQ5ZiugBZwW6ZjXylQIWAmvuiBAIqa","url_list":["https://p3-sign.douyinpic.com/tos-cn-p-0015/oo4PsWKEQ5ZiugBZwW6ZjXylQIWAmvuiBAIqa~noop.jpeg?lk3s=bfd515bb\u0026x-expires=1722340800\u0026x-signature=fUp%2BWLE%2FQ24%2B9iw%2BX4%2FO2j4Zw00%3D\u0026from=3218412987","https://p26-sign.douyinpic.com/tos-cn-p-0015/oo4PsWKEQ5ZiugBZwW6ZjXylQIWAmvuiBAIqa~noop.jpeg?lk3s=bfd515bb\u0026x-expires=1722340800\u0026x-signature=tbqQfz72RyH2Btq1hRcnORsqtAU%3D\u0026from=3218412987","https://p11-sign.douyinpic.com/tos-cn-p-0015/oo4PsWKEQ5ZiugBZwW6ZjXylQIWAmvuiBAIqa~noop.jpeg?lk3s=bfd515bb\u0026x-expires=1722340800\u0026x-signature=%2B3s%2BHEhgE7CtcvfGxKUqk2ulVAQ%3D\u0026from=3218412987"]},"word_sub_board":null,"word_type":1},{"aweme_infos":null,"challenge_id":"","display_style":0,"drift_info":null,"event_time":1722298135,"group_id":"7394829062265754899","hot_value":4569205,"hotlist_param":"{\"version\":1}","label":0,"position":31,"related_words":null,"sentence_id":"1780896","video_count":1,"view_count":2822590,"word":"警方回应男子用枪状物体指人","word_cover":{"uri":"tos-cn-p-0015/oQEfQNyf3MNIM9A9GcpmaCFDcJiDLmgAA046nB","url_list":["https://p3-sign.douyinpic.com/tos-cn-p-0015/oQEfQNyf3MNIM9A9GcpmaCFDcJiDLmgAA046nB~noop.jpeg?lk3s=bfd515bb\u0026x-expires=1722340800\u0026x-signature=lMKue19Ihzi%2BBQSWCYcTMGVfvY4%3D\u0026from=3218412987","https://p11-sign.douyinpic.com/tos-cn-p-0015/oQEfQNyf3MNIM9A9GcpmaCFDcJiDLmgAA046nB~noop.jpeg?lk3s=bfd515bb\u0026x-expires=1722340800\u0026x-signature=JijCpWH%2FhBKEQve3VY%2FL6%2FyWkCA%3D\u0026from=3218412987","https://p26-sign.douyinpic.com/tos-cn-p-0015/oQEfQNyf3MNIM9A9GcpmaCFDcJiDLmgAA046nB~noop.jpeg?lk3s=bfd515bb\u0026x-expires=1722340800\u0026x-signature=FrEBWNMX8g%2BFYpbVGYhImm0699Q%3D\u0026from=3218412987"]},"word_sub_board":null,"word_type":1},{"aweme_infos":null,"can_extend_detail":false,"challenge_id":"","display_style":0,"drift_info":null,"event_time":1722240157,"group_id":"7394073790169224460","hot_value":4566945,"hotlist_param":"{\"version\":1}","label":0,"position":32,"related_words":null,"sentence_id":"1779857","video_count":1,"view_count":623950,"word":"外交部回应是否会调停俄乌战争","word_cover":{"uri":"tos-cn-p-0015/oIf7eTICTDh9tnGFBohnTMAIGeALLBFtRCKNpI","url_list":["https://p3-sign.douyinpic.com/tos-cn-p-0015/oIf7eTICTDh9tnGFBohnTMAIGeALLBFtRCKNpI~noop.jpeg?lk3s=bfd515bb\u0026x-expires=1722340800\u0026x-signature=arO4a7XZmYN38B%2FH2amu6MsP6gU%3D\u0026from=3218412987","https://p11-sign.douyinpic.com/tos-cn-p-0015/oIf7eTICTDh9tnGFBohnTMAIGeALLBFtRCKNpI~noop.jpeg?lk3s=bfd515bb\u0026x-expires=1722340800\u0026x-signature=j%2Bs06Hy9oDhpYYpUAd3X4SbmnMQ%3D\u0026from=3218412987","https://p26-sign.douyinpic.com/tos-cn-p-0015/oIf7eTICTDh9tnGFBohnTMAIGeALLBFtRCKNpI~noop.jpeg?lk3s=bfd515bb\u0026x-expires=1722340800\u0026x-signature=0EkRXGYi1R45G%2FpOq9LVk3I3KSw%3D\u0026from=3218412987"]},"word_sub_board":null,"word_type":1},{"aweme_infos":null,"can_extend_detail":false,"challenge_id":"","display_style":0,"drift_info":null,"event_time":1722301325,"group_id":"7397050177683821851","hot_value":4558584,"hotlist_param":"{\"version\":1}","label":0,"position":33,"related_words":null,"sentence_id":"1780544","video_count":1,"view_count":370607,"word":"戈兰高地遭袭事件伤者情况","word_cover":{"uri":"tos-cn-p-0015/owfyODKNqBAFzweEBIG2gSAvpVrgsmJkDA9oE2","url_list":["https://p3-sign.douyinpic.com/tos-cn-p-0015/owfyODKNqBAFzweEBIG2gSAvpVrgsmJkDA9oE2~noop.jpeg?lk3s=bfd515bb\u0026x-expires=1722340800\u0026x-signature=CjnxUeURt20SaDsaIm%2F629DM6nc%3D\u0026from=3218412987","https://p26-sign.douyinpic.com/tos-cn-p-0015/owfyODKNqBAFzweEBIG2gSAvpVrgsmJkDA9oE2~noop.jpeg?lk3s=bfd515bb\u0026x-expires=1722340800\u0026x-signature=WtCTVTzu9RcQz38XxDpCf3Wo%2B7c%3D\u0026from=3218412987","https://p11-sign.douyinpic.com/tos-cn-p-0015/owfyODKNqBAFzweEBIG2gSAvpVrgsmJkDA9oE2~noop.jpeg?lk3s=bfd515bb\u0026x-expires=1722340800\u0026x-signature=eAp5xSNCLs7opDCe9SapPh%2FyXGU%3D\u0026from=3218412987"]},"word_sub_board":null,"word_type":1},{"aweme_infos":null,"can_extend_detail":false,"challenge_id":"","display_style":0,"drift_info":null,"event_time":1722304838,"group_id":"7395549957363111220","hot_value":4556790,"hotlist_param":"{\"version\":1}","label":0,"position":34,"related_words":null,"sentence_id":"1780599","video_count":1,"view_count":349750,"word":"瓦格纳雇佣兵用石头反抗被射杀","word_cover":{"uri":"tos-cn-p-0015/oQAAKaqQIcmQfBemi9DEjQCACqg9ECFgSUHA6D","url_list":["https://p11-sign.douyinpic.com/tos-cn-p-0015/oQAAKaqQIcmQfBemi9DEjQCACqg9ECFgSUHA6D~noop.jpeg?lk3s=bfd515bb\u0026x-expires=1722340800\u0026x-signature=h5hAazWR%2B4zvGmzgbvd9tgZwbyk%3D\u0026from=3218412987","https://p3-sign.douyinpic.com/tos-cn-p-0015/oQAAKaqQIcmQfBemi9DEjQCACqg9ECFgSUHA6D~noop.jpeg?lk3s=bfd515bb\u0026x-expires=1722340800\u0026x-signature=N6t90AsgWOoPz7cuFJroR1jqzE0%3D\u0026from=3218412987","https://p26-sign.douyinpic.com/tos-cn-p-0015/oQAAKaqQIcmQfBemi9DEjQCACqg9ECFgSUHA6D~noop.jpeg?lk3s=bfd515bb\u0026x-expires=1722340800\u0026x-signature=RCjdvllyX7voXvi6s54hVneZiXE%3D\u0026from=3218412987"]},"word_sub_board":null,"word_type":1},{"aweme_infos":null,"challenge_id":"","display_style":0,"drift_info":null,"event_time":1722308911,"group_id":"7394354423029749004","hot_value":4544464,"hotlist_param":"{\"version\":1}","label":0,"position":35,"related_words":null,"sentence_id":"1780684","video_count":3,"view_count":499175,"word":"暴雨过后高铁变了个色","word_cover":{"uri":"tos-cn-p-0015/oYe8QdAAAnxAPQfYPsI501fkftfEsHJdhw4Dx8","url_list":["https://p3-sign.douyinpic.com/tos-cn-p-0015/oYe8QdAAAnxAPQfYPsI501fkftfEsHJdhw4Dx8~noop.jpeg?lk3s=bfd515bb\u0026x-expires=1722340800\u0026x-signature=I2noH66SjziHMosjNXObTfWCa6g%3D\u0026from=3218412987","https://p26-sign.douyinpic.com/tos-cn-p-0015/oYe8QdAAAnxAPQfYPsI501fkftfEsHJdhw4Dx8~noop.jpeg?lk3s=bfd515bb\u0026x-expires=1722340800\u0026x-signature=aZOTyppR0%2BQpLDyYyS%2BoEF7%2B5wk%3D\u0026from=3218412987","https://p11-sign.douyinpic.com/tos-cn-p-0015/oYe8QdAAAnxAPQfYPsI501fkftfEsHJdhw4Dx8~noop.jpeg?lk3s=bfd515bb\u0026x-expires=1722340800\u0026x-signature=bIu3oc9ztX9IRxPfHX9HWuOtEJQ%3D\u0026from=3218412987"]},"word_sub_board":null,"word_type":1},{"aweme_infos":null,"can_extend_detail":false,"challenge_id":"","display_style":0,"drift_info":null,"event_time":1722254975,"group_id":"7394105690044077324","hot_value":4534828,"hotlist_param":"{\"version\":1}","label":0,"position":36,"related_words":null,"sentence_id":"1780207","video_count":1,"view_count":174761,"word":"参院民主党领袖：特朗普后悔选万斯","word_cover":{"uri":"tos-cn-i-dy/1446644ebc4141b5a1c84b64136655f8","url_list":["https://p11-sign.douyinpic.com/tos-cn-i-dy/1446644ebc4141b5a1c84b64136655f8~noop.jpeg?lk3s=bfd515bb\u0026x-expires=1722340800\u0026x-signature=IGoyWOsrSNUUZtRXwt4BZRIptKM%3D\u0026from=3218412987","https://p3-sign.douyinpic.com/tos-cn-i-dy/1446644ebc4141b5a1c84b64136655f8~noop.jpeg?lk3s=bfd515bb\u0026x-expires=1722340800\u0026x-signature=tX10LdGJubbtzVAA22L4C3WoxT8%3D\u0026from=3218412987","https://p9-sign.douyinpic.com/tos-cn-i-dy/1446644ebc4141b5a1c84b64136655f8~noop.jpeg?lk3s=bfd515bb\u0026x-expires=1722340800\u0026x-signature=Zv1nzfrhUNNlC22I2SyteILbB0U%3D\u0026from=3218412987"]},"word_sub_board":null,"word_type":1},{"aweme_infos":null,"challenge_id":"","display_style":0,"drift_info":null,"event_time":1722236441,"group_id":"7394141104592344383","hot_value":4528243,"hotlist_param":"{\"version\":1}","label":0,"position":37,"related_words":null,"sentence_id":"1779842","video_count":2,"view_count":564075,"word":"女子高铁遭遇男子霸座充电","word_cover":{"uri":"tos-cn-p-0015/owIn9zgRmQCRAeA1NBpFzWMEQyDIWJAkkgfDD7","url_list":["https://p26-sign.douyinpic.com/tos-cn-p-0015/owIn9zgRmQCRAeA1NBpFzWMEQyDIWJAkkgfDD7~noop.jpeg?lk3s=bfd515bb\u0026x-expires=1722340800\u0026x-signature=iEenWNl%2Bc9k6qD%2BJJrST25g%2BoLA%3D\u0026from=3218412987","https://p3-sign.douyinpic.com/tos-cn-p-0015/owIn9zgRmQCRAeA1NBpFzWMEQyDIWJAkkgfDD7~noop.jpeg?lk3s=bfd515bb\u0026x-expires=1722340800\u0026x-signature=O%2Bzh7H%2BPt%2B5Npu24nmCpMIaHDcU%3D\u0026from=3218412987","https://p11-sign.douyinpic.com/tos-cn-p-0015/owIn9zgRmQCRAeA1NBpFzWMEQyDIWJAkkgfDD7~noop.jpeg?lk3s=bfd515bb\u0026x-expires=1722340800\u0026x-signature=chK2D4mxLI6rsRrqa3iWs2bgpuM%3D\u0026from=3218412987"]},"word_sub_board":null,"word_type":1},{"aweme_infos":null,"can_extend_detail":false,"challenge_id":"","display_style":0,"drift_info":null,"event_time":1722261214,"group_id":"7395892258576962854","hot_value":4523522,"hotlist_param":"{\"version\":1}","label":0,"position":38,"related_words":null,"sentence_id":"1780342","video_count":3,"view_count":1369445,"word":"园方回应猴子爱凹造型","word_cover":{"uri":"tos-cn-p-0015/o0iiuieAEAAfUIOnBzxg7uNSDBi6IXUB6aDijx","url_list":["https://p26-sign.douyinpic.com/tos-cn-p-0015/o0iiuieAEAAfUIOnBzxg7uNSDBi6IXUB6aDijx~noop.jpeg?lk3s=bfd515bb\u0026x-expires=1722340800\u0026x-signature=lFPkByj8hXRWaFX7YZ9HcagwRgI%3D\u0026from=3218412987","https://p3-sign.douyinpic.com/tos-cn-p-0015/o0iiuieAEAAfUIOnBzxg7uNSDBi6IXUB6aDijx~noop.jpeg?lk3s=bfd515bb\u0026x-expires=1722340800\u0026x-signature=VxY%2BOPf5xz5TuYTXBenEGD4Pcu0%3D\u0026from=3218412987","https://p11-sign.douyinpic.com/tos-cn-p-0015/o0iiuieAEAAfUIOnBzxg7uNSDBi6IXUB6aDijx~noop.jpeg?lk3s=bfd515bb\u0026x-expires=1722340800\u0026x-signature=0rdlWDqi6nkwH%2BO9ohPAVUTkKqM%3D\u0026from=3218412987"]},"word_sub_board":null,"word_type":1},{"aweme_infos":null,"can_extend_detail":false,"challenge_id":"","display_style":0,"drift_info":null,"event_time":1722314806,"group_id":"7395469741089019162","hot_value":4513329,"hotlist_param":"{\"version\":1}","label":0,"position":39,"related_words":null,"sentence_id":"1780893","video_count":2,"view_count":173860,"word":"委内瑞拉爆发集会要求重新计票","word_cover":{"uri":"tos-cn-p-0015/oU5Bk8IQeAS7MeTQCz7QArCaiBUXIYmLNerVKt","url_list":["https://p11-sign.douyinpic.com/tos-cn-p-0015/oU5Bk8IQeAS7MeTQCz7QArCaiBUXIYmLNerVKt~noop.jpeg?lk3s=bfd515bb\u0026x-expires=1722340800\u0026x-signature=ruIfbq9yFd7VR7FoX2oIyiZV%2BSw%3D\u0026from=3218412987","https://p26-sign.douyinpic.com/tos-cn-p-0015/oU5Bk8IQeAS7MeTQCz7QArCaiBUXIYmLNerVKt~noop.jpeg?lk3s=bfd515bb\u0026x-expires=1722340800\u0026x-signature=SKTwjYhIB8LwcveQLMh3qw9poao%3D\u0026from=3218412987","https://p9-sign.douyinpic.com/tos-cn-p-0015/oU5Bk8IQeAS7MeTQCz7QArCaiBUXIYmLNerVKt~noop.jpeg?lk3s=bfd515bb\u0026x-expires=1722340800\u0026x-signature=BI9HfqWclrCfhO9jteyd5WiGseI%3D\u0026from=3218412987"]},"word_sub_board":null,"word_type":1},{"aweme_infos":null,"can_extend_detail":false,"challenge_id":"","display_style":0,"drift_info":null,"event_time":1722245873,"group_id":"7395465341357724963","hot_value":4505718,"hotlist_param":"{\"version\":1}","label":0,"position":40,"related_words":null,"sentence_id":"1780017","video_count":2,"view_count":956305,"word":"教育局回应学生玩梗被赶下台","word_cover":{"uri":"tos-cn-p-0015/oAlhEmBzAggIQieApiWnfBLAn0lBUiwE7CGYPA","url_list":["https://p26-sign.douyinpic.com/tos-cn-p-0015/oAlhEmBzAggIQieApiWnfBLAn0lBUiwE7CGYPA~noop.jpeg?lk3s=bfd515bb\u0026x-expires=1722340800\u0026x-signature=lfnCrbexjKdFFLmxSY4bH9%2Fusho%3D\u0026from=3218412987","https://p3-sign.douyinpic.com/tos-cn-p-0015/oAlhEmBzAggIQieApiWnfBLAn0lBUiwE7CGYPA~noop.jpeg?lk3s=bfd515bb\u0026x-expires=1722340800\u0026x-signature=P7YwosmcUYYPfQtIvMYzwvaG2VY%3D\u0026from=3218412987","https://p11-sign.douyinpic.com/tos-cn-p-0015/oAlhEmBzAggIQieApiWnfBLAn0lBUiwE7CGYPA~noop.jpeg?lk3s=bfd515bb\u0026x-expires=1722340800\u0026x-signature=D9YLhb6L4AkPyYHNVFMKvwNgg%2B0%3D\u0026from=3218412987"]},"word_sub_board":null,"word_type":1},{"aweme_infos":null,"can_extend_detail":false,"challenge_id":"","display_style":0,"drift_info":null,"event_time":1722307829,"group_id":"7394569464548070710","hot_value":4498677,"hotlist_param":"{\"version\":1}","label":0,"position":41,"related_words":null,"sentence_id":"1780650","video_count":1,"view_count":4234225,"word":"黄雨婷爸爸说准备好了食饼筒","word_cover":{"uri":"tos-cn-p-0015/o0yIgi1BeHlEzAhvnAzUaewIlLFBABiBCs0A3G","url_list":["https://p3-sign.douyinpic.com/tos-cn-p-0015/o0yIgi1BeHlEzAhvnAzUaewIlLFBABiBCs0A3G~noop.jpeg?lk3s=bfd515bb\u0026x-expires=1722340800\u0026x-signature=oalnEnrR8VRzR%2BMZQVHl5Kvig7s%3D\u0026from=3218412987","https://p11-sign.douyinpic.com/tos-cn-p-0015/o0yIgi1BeHlEzAhvnAzUaewIlLFBABiBCs0A3G~noop.jpeg?lk3s=bfd515bb\u0026x-expires=1722340800\u0026x-signature=riBKLL4FPs60GFOUojkC7s9olyY%3D\u0026from=3218412987","https://p26-sign.douyinpic.com/tos-cn-p-0015/o0yIgi1BeHlEzAhvnAzUaewIlLFBABiBCs0A3G~noop.jpeg?lk3s=bfd515bb\u0026x-expires=1722340800\u0026x-signature=DDwxD66BWZ6F8IsVklWK2LI2FF4%3D\u0026from=3218412987"]},"word_sub_board":null,"word_type":1},{"aweme_infos":null,"challenge_id":"","display_style":0,"drift_info":null,"event_time":1722255825,"group_id":"7394213553131296036","hot_value":4497745,"hotlist_param":"{\"version\":1}","label":0,"position":42,"related_words":null,"sentence_id":"1780245","video_count":2,"view_count":302985,"word":"男子发现解放军墓地帮寻找家人","word_cover":{"uri":"tos-cn-p-0015/oQNmpFD9IABEbyedfAAgIAoFn3ncTU1a3ch9Dd","url_list":["https://p3-sign.douyinpic.com/tos-cn-p-0015/oQNmpFD9IABEbyedfAAgIAoFn3ncTU1a3ch9Dd~noop.jpeg?lk3s=bfd515bb\u0026x-expires=1722340800\u0026x-signature=3NKNn9KZxVx78P4xuHLFF15xKl0%3D\u0026from=3218412987","https://p26-sign.douyinpic.com/tos-cn-p-0015/oQNmpFD9IABEbyedfAAgIAoFn3ncTU1a3ch9Dd~noop.jpeg?lk3s=bfd515bb\u0026x-expires=1722340800\u0026x-signature=oQc6TCUxkAxgNzRVYWxeXuZw7Hc%3D\u0026from=3218412987","https://p11-sign.douyinpic.com/tos-cn-p-0015/oQNmpFD9IABEbyedfAAgIAoFn3ncTU1a3ch9Dd~noop.jpeg?lk3s=bfd515bb\u0026x-expires=1722340800\u0026x-signature=p8BM4dKafl5Hi6Tu7dyvIdxk6L4%3D\u0026from=3218412987"]},"word_sub_board":null,"word_type":1},{"aweme_infos":null,"can_extend_detail":false,"challenge_id":"","display_style":0,"drift_info":null,"event_time":1722257799,"group_id":"7396837820944274714","hot_value":4486972,"hotlist_param":"{\"version\":1}","label":0,"position":43,"related_words":null,"sentence_id":"1780255","video_count":2,"view_count":2348130,"word":"俄罗斯民众排队打卡焦作舰","word_cover":{"uri":"tos-cn-p-0015/oUAw8eIgNNAiki8kaTez2UPXhhBXABQIcETzKn","url_list":["https://p3-sign.douyinpic.com/tos-cn-p-0015/oUAw8eIgNNAiki8kaTez2UPXhhBXABQIcETzKn~noop.jpeg?lk3s=bfd515bb\u0026x-expires=1722340800\u0026x-signature=qYx1aHANu2KnVhpDGBBpFGfn78E%3D\u0026from=3218412987","https://p26-sign.douyinpic.com/tos-cn-p-0015/oUAw8eIgNNAiki8kaTez2UPXhhBXABQIcETzKn~noop.jpeg?lk3s=bfd515bb\u0026x-expires=1722340800\u0026x-signature=aD403JvF7R6rjEwrcKDIunnEZdE%3D\u0026from=3218412987","https://p11-sign.douyinpic.com/tos-cn-p-0015/oUAw8eIgNNAiki8kaTez2UPXhhBXABQIcETzKn~noop.jpeg?lk3s=bfd515bb\u0026x-expires=1722340800\u0026x-signature=EPSPcyPhN7J9av15GojdlAx7xUs%3D\u0026from=3218412987"]},"word_sub_board":null,"word_type":1},{"aweme_infos":null,"challenge_id":"","display_style":0,"drift_info":null,"event_time":1722302386,"group_id":"7395894602781283618","hot_value":4485232,"hotlist_param":"{\"version\":1}","label":0,"position":44,"related_words":null,"sentence_id":"1780659","video_count":1,"view_count":630847,"word":"祖传雕像被警方追回移交博物馆","word_cover":{"uri":"tos-cn-p-0015/ooDBUXnACe2B1LyFBgCeMsvYA6AinmizgETIRO","url_list":["https://p26-sign.douyinpic.com/tos-cn-p-0015/ooDBUXnACe2B1LyFBgCeMsvYA6AinmizgETIRO~noop.jpeg?lk3s=bfd515bb\u0026x-expires=1722340800\u0026x-signature=NrXaolnRma77JbB7GR%2BS3PLdGAQ%3D\u0026from=3218412987","https://p3-sign.douyinpic.com/tos-cn-p-0015/ooDBUXnACe2B1LyFBgCeMsvYA6AinmizgETIRO~noop.jpeg?lk3s=bfd515bb\u0026x-expires=1722340800\u0026x-signature=0wtaT4MDIB%2BAK71pRpHAeykOiLY%3D\u0026from=3218412987","https://p11-sign.douyinpic.com/tos-cn-p-0015/ooDBUXnACe2B1LyFBgCeMsvYA6AinmizgETIRO~noop.jpeg?lk3s=bfd515bb\u0026x-expires=1722340800\u0026x-signature=XHqJRO3NUedeFTtInFRqCik%2BVZQ%3D\u0026from=3218412987"]},"word_sub_board":null,"word_type":1},{"aweme_infos":null,"can_extend_detail":false,"challenge_id":"","display_style":0,"drift_info":null,"event_time":1722261816,"group_id":"7395434756701558016","hot_value":4483524,"hotlist_param":"{\"version\":1}","label":0,"position":45,"related_words":null,"sentence_id":"1780339","video_count":1,"view_count":12283740,"word":"盛李豪的同学小学时就已拿到签名","word_cover":{"uri":"tos-cn-p-0015/o0U2A8nieCDftGubggB8gIQUEAgzk4Bx1g0AiB","url_list":["https://p3-sign.douyinpic.com/tos-cn-p-0015/o0U2A8nieCDftGubggB8gIQUEAgzk4Bx1g0AiB~noop.jpeg?lk3s=bfd515bb\u0026x-expires=1722340800\u0026x-signature=DqCco%2BQpcpuQUhSmr%2BO8W8IxA2c%3D\u0026from=3218412987","https://p11-sign.douyinpic.com/tos-cn-p-0015/o0U2A8nieCDftGubggB8gIQUEAgzk4Bx1g0AiB~noop.jpeg?lk3s=bfd515bb\u0026x-expires=1722340800\u0026x-signature=ZBspTS01GGX1oZVINQSwWqcuYXs%3D\u0026from=3218412987","https://p26-sign.douyinpic.com/tos-cn-p-0015/o0U2A8nieCDftGubggB8gIQUEAgzk4Bx1g0AiB~noop.jpeg?lk3s=bfd515bb\u0026x-expires=1722340800\u0026x-signature=5g8YX4dfx%2Fmwy99UMVA7kaRjrdY%3D\u0026from=3218412987"]},"word_sub_board":null,"word_type":1},{"aweme_infos":null,"can_extend_detail":false,"challenge_id":"","display_style":0,"drift_info":null,"event_time":1722266617,"group_id":"7395849051273696549","hot_value":4482301,"hotlist_param":"{\"version\":1}","label":0,"position":46,"related_words":null,"sentence_id":"1780442","video_count":1,"view_count":322625,"word":"撞船事件大陆代表及家属抵金门","word_cover":{"uri":"tos-cn-p-0015/o8UnuPgQEuDApNJF7EBWemsF6BnA9AErQulYfo","url_list":["https://p3-sign.douyinpic.com/tos-cn-p-0015/o8UnuPgQEuDApNJF7EBWemsF6BnA9AErQulYfo~noop.jpeg?lk3s=bfd515bb\u0026x-expires=1722340800\u0026x-signature=NpIltN6wdyeoIIiS1dh9sRJ4NGI%3D\u0026from=3218412987","https://p9-sign.douyinpic.com/tos-cn-p-0015/o8UnuPgQEuDApNJF7EBWemsF6BnA9AErQulYfo~noop.jpeg?lk3s=bfd515bb\u0026x-expires=1722340800\u0026x-signature=0JDpn13NCXeqPQxQXDvXk1VXmNA%3D\u0026from=3218412987","https://p26-sign.douyinpic.com/tos-cn-p-0015/o8UnuPgQEuDApNJF7EBWemsF6BnA9AErQulYfo~noop.jpeg?lk3s=bfd515bb\u0026x-expires=1722340800\u0026x-signature=1jpuFs%2BQ4KDqR0wejdxOYqLLCOw%3D\u0026from=3218412987"]},"word_sub_board":null,"word_type":1},{"aweme_infos":null,"challenge_id":"","display_style":0,"drift_info":null,"event_time":1722312623,"group_id":"7395986611216028938","hot_value":4473834,"hotlist_param":"{\"version\":1}","label":0,"position":47,"related_words":null,"sentence_id":"1780830","video_count":1,"view_count":856978,"word":"两人捡钱包归还却被告知少一千元","word_cover":{"uri":"tos-cn-p-0015/owa2SzjCfABOEiBvABMoHwIgRie2CVs3ADiIAL","url_list":["https://p26-sign.douyinpic.com/tos-cn-p-0015/owa2SzjCfABOEiBvABMoHwIgRie2CVs3ADiIAL~noop.jpeg?lk3s=bfd515bb\u0026x-expires=1722340800\u0026x-signature=QwLhPh%2BZGoikTX7VttyDlFz8YPE%3D\u0026from=3218412987","https://p3-sign.douyinpic.com/tos-cn-p-0015/owa2SzjCfABOEiBvABMoHwIgRie2CVs3ADiIAL~noop.jpeg?lk3s=bfd515bb\u0026x-expires=1722340800\u0026x-signature=T8Dhi6bfdKk7f0J0rOIOgzlC2kQ%3D\u0026from=3218412987","https://p11-sign.douyinpic.com/tos-cn-p-0015/owa2SzjCfABOEiBvABMoHwIgRie2CVs3ADiIAL~noop.jpeg?lk3s=bfd515bb\u0026x-expires=1722340800\u0026x-signature=XXub9s1%2B0jhsRCy2f21W9GPW9XM%3D\u0026from=3218412987"]},"word_sub_board":null,"word_type":1},{"aweme_infos":null,"challenge_id":"","display_style":0,"drift_info":null,"event_time":1722255084,"group_id":"7395886049026708772","hot_value":4468484,"hotlist_param":"{\"version\":1}","label":0,"position":48,"related_words":null,"sentence_id":"1780201","video_count":1,"view_count":954678,"word":"记者暗访贵阳火车站住宿乱象","word_cover":{"uri":"tos-cn-p-0015/oof0O50DUBAiuYXEBIOw7GAsKE1guzhkBAeniW","url_list":["https://p3-sign.douyinpic.com/tos-cn-p-0015/oof0O50DUBAiuYXEBIOw7GAsKE1guzhkBAeniW~noop.jpeg?lk3s=bfd515bb\u0026x-expires=1722340800\u0026x-signature=XS17C44LTOQl9I%2FATK0VlNEz0Oc%3D\u0026from=3218412987","https://p26-sign.douyinpic.com/tos-cn-p-0015/oof0O50DUBAiuYXEBIOw7GAsKE1guzhkBAeniW~noop.jpeg?lk3s=bfd515bb\u0026x-expires=1722340800\u0026x-signature=mUvrW68fFqcPCEoW9XCPumSHO%2Fw%3D\u0026from=3218412987","https://p9-sign.douyinpic.com/tos-cn-p-0015/oof0O50DUBAiuYXEBIOw7GAsKE1guzhkBAeniW~noop.jpeg?lk3s=bfd515bb\u0026x-expires=1722340800\u0026x-signature=UO4MuaLm1TOk6%2FBVSjlsaS1h8R0%3D\u0026from=3218412987"]},"word_sub_board":null,"word_type":1},{"aweme_infos":null,"can_extend_detail":false,"challenge_id":"","display_style":0,"drift_info":null,"event_time":1722262827,"group_id":"7395458751762044200","hot_value":4456248,"hotlist_param":"{\"version\":1}","label":0,"position":49,"related_words":null,"sentence_id":"1780369","video_count":1,"view_count":6094020,"word":"教练辟谣在射击摊挖掘盛李豪","word_cover":{"uri":"tos-cn-p-0015/ooGzINEDEAfAviEFnm5nA46IS9F439ApeuB02g","url_list":["https://p11-sign.douyinpic.com/tos-cn-p-0015/ooGzINEDEAfAviEFnm5nA46IS9F439ApeuB02g~noop.jpeg?lk3s=bfd515bb\u0026x-expires=1722340800\u0026x-signature=Ma2NnHTKNZ7jO0BoA90CkPtprNw%3D\u0026from=3218412987","https://p3-sign.douyinpic.com/tos-cn-p-0015/ooGzINEDEAfAviEFnm5nA46IS9F439ApeuB02g~noop.jpeg?lk3s=bfd515bb\u0026x-expires=1722340800\u0026x-signature=HU4Sl%2BSgjHcx8JYEI%2F4YPySRTFg%3D\u0026from=3218412987","https://p26-sign.douyinpic.com/tos-cn-p-0015/ooGzINEDEAfAviEFnm5nA46IS9F439ApeuB02g~noop.jpeg?lk3s=bfd515bb\u0026x-expires=1722340800\u0026x-signature=iJ9cGxP%2FPTxxVIY07pPl%2FLWDlxQ%3D\u0026from=3218412987"]},"word_sub_board":null,"word_type":1},{"aweme_infos":null,"challenge_id":"","display_style":0,"drift_info":null,"event_time":1722311413,"group_id":"7394429206778877195","hot_value":4455063,"hotlist_param":"{\"version\":1}","label":0,"position":50,"related_words":null,"sentence_id":"1780757","video_count":1,"view_count":332492,"word":"村支书转移民众自己女儿不幸遇难","word_cover":{"uri":"tos-cn-p-0015/oMYB8QeMAgmCWIeX8oN7BEAWI6ofWUIkM5UWaa","url_list":["https://p11-sign.douyinpic.com/tos-cn-p-0015/oMYB8QeMAgmCWIeX8oN7BEAWI6ofWUIkM5UWaa~noop.jpeg?lk3s=bfd515bb\u0026x-expires=1722340800\u0026x-signature=fq2HY8Os5%2F%2FKv4jQ%2FhwOLcUBTBo%3D\u0026from=3218412987","https://p26-sign.douyinpic.com/tos-cn-p-0015/oMYB8QeMAgmCWIeX8oN7BEAWI6ofWUIkM5UWaa~noop.jpeg?lk3s=bfd515bb\u0026x-expires=1722340800\u0026x-signature=5n6yjJouSfRTu2NxKa8P5B1uYwg%3D\u0026from=3218412987","https://p3-sign.douyinpic.com/tos-cn-p-0015/oMYB8QeMAgmCWIeX8oN7BEAWI6ofWUIkM5UWaa~noop.jpeg?lk3s=bfd515bb\u0026x-expires=1722340800\u0026x-signature=G3rashMpvV%2FdrCRapZFYn3EyOGI%3D\u0026from=3218412987"]},"word_sub_board":null,"word_type":1}]},"extra":{"fatal_item_ids":[],"logid":"20240730141302C17A7DCFCAE3E3022F5A","now":1722319982000},"log_pb":{"impr_id":"20240730141302C17A7DCFCAE3E3022F5A"},"status_code":0}